{"name":"Where Incidents Took Place By Precinct - Staten Island","desc":"Where Incidents that Led to a Complaint Took Place by Precinct - Staten Island.","data":[{"2009":220,"2010":182,"2011":149,"2012":177,"2013":124,"precinct":"120th Precinct","total":852},{"2009":0,"2010":0,"2011":0,"2012":0,"2013":38,"precinct":"121st Precinct","total":38},{"2009":72,"2010":55,"2011":64,"2012":63,"2013":63,"precinct":"122nd Precinct","total":317},{"2009":24,"2010":24,"2011":16,"2012":17,"2013":12,"precinct":"123rd Precinct","total":93},{"2009":316,"2010":261,"2011":229,"2012":257,"2013":237,"precinct":"Staten Island Total","total":1300},{"2009":98,"2010":78,"2011":48,"2012":80,"2013":92,"precinct":"Outside City/ Unidentified","total":396}]}